quickdataanalysis/__init__.py
quickdataanalysis/data_analysis.py
quickdataanalysis/exception/__init__.py
quickdataanalysis/exception/quickdataanalysis_exception.py
quickdataanalysis-0.0.7.dist-info/LICENSE
quickdataanalysis-0.0.7.dist-info/METADATA
quickdataanalysis-0.0.7.dist-info/WHEEL
quickdataanalysis-0.0.7.dist-info/top_level.txt
quickdataanalysis-0.0.7.dist-info/RECORD
