Metadata-Version: 2.1
Name: quickdataanalysis
Version: 0.0.7
Summary: Kick start your data analysis with these functions
Home-page: https://github.com/Santhoshkumard11/quickdataanalysis
Author: Santhoshkumard11
Maintainer: Santhoshkumard11
License: MIT
Platform: UNKNOWN
Classifier: Development Status :: 4 - Beta
Classifier: Operating System :: OS Independent
Classifier: Intended Audience :: Developers
Classifier: Programming Language :: Python
Classifier: Programming Language :: Python :: 3
Classifier: Topic :: Software Development :: Libraries
Requires-Dist: pandas (>=1.0.1)
